README.txt
setup.py
mechpress/__init__.py
mechpress/automation_345.py
mechpress/automation_345_cv.py
mechpress/bed.py
mechpress/crown.py
mechpress/ed.py
mechpress/flywheel_energy.py
mechpress/gear_geometry.py
mechpress/gear_strength.py
mechpress/hydrodynamic_bush.py
mechpress/key_size.py
mechpress/ld.py
mechpress/line_equation.py
mechpress/metric_thread.py
mechpress/polynomial_345.py
mechpress/polynomial_345_cv.py
mechpress/power_screw.py
mechpress/section_mi.py
mechpress/shaft.py
mechpress/slide.py
mechpress/test.py
mechpress.egg-info/PKG-INFO
mechpress.egg-info/SOURCES.txt
mechpress.egg-info/dependency_links.txt
mechpress.egg-info/top_level.txt