Metadata-Version: 1.1
Name: mechpress
Version: 0.0.11
Summary: package for mechanical press design
Home-page: UNKNOWN
Author: Sanchit
Author-email: sanchitsharma84@gmail.com
License: MIT
Keywords: mechanical press
Platform: UNKNOWN
Classifier: Development Status :: 1 - Planning
Classifier: Intended Audience :: Education
Classifier: Operating System :: Microsoft :: Windows :: Windows 10
Classifier: License :: OSI Approved :: MIT License
Classifier: Programming Language :: Python :: 3
